.gitignore
COPYING
COPYING.LESSER
MANIFEST.in
README.rst
requirements.txt
setup.py
examples/generate_data.py
examples/generate_diatomic.py
examples/plotter.py
examples/psi4_demo.ipynb
fermilibpluginpsi4/__init__.py
fermilibpluginpsi4/_psi4_conversion_functions.py
fermilibpluginpsi4/_psi4_template
fermilibpluginpsi4/_run_psi4.py
fermilibpluginpsi4/_version.py
fermilibpluginpsi4.egg-info/PKG-INFO
fermilibpluginpsi4.egg-info/SOURCES.txt
fermilibpluginpsi4.egg-info/dependency_links.txt
fermilibpluginpsi4.egg-info/requires.txt
fermilibpluginpsi4.egg-info/top_level.txt