Metadata-Version: 1.0
Name: fermilibpluginpsi4
Version: 0.1a1
Summary: A plugin allowing FermiLib to interface with Psi4.
Home-page: http://www.projectq.ch
Author: FermiLib plugin Psi4 developers
Author-email: fermilib@projectq.ch
License: GNU Lesser General Public License (LGPL), Version 3 or any later version
Platform: UNKNOWN
